{
  "1": {
    "HRV": {
      "mean": 82.43773663803545,
      "sd_within": 15.0
    },
    "RHR": {
      "mean": 43.840063575038016,
      "sd_within": 5.0
    },
    "SleepDur": {
      "mean": 8.300180478322583,
      "sd_within": 0.8
    },
    "SleepEff": {
      "mean": 0.9282169414917364,
      "sd_within": 0.05
    }
  },
  "2": {
    "HRV": {
      "mean": 69.58256394510146,
      "sd_within": 15.0
    },
    "RHR": {
      "mean": 48.51136161266914,
      "sd_within": 5.0
    },
    "SleepDur": {
      "mean": 7.873502963062567,
      "sd_within": 0.8
    },
    "SleepEff": {
      "mean": 0.8994959652748714,
      "sd_within": 0.05
    }
  },
  "3": {
    "HRV": {
      "mean": 87.03518379890262,
      "sd_within": 15.0
    },
    "RHR": {
      "mean": 51.111167741715796,
      "sd_within": 5.0
    },
    "SleepDur": {
      "mean": 8.026412279024486,
      "sd_within": 0.8
    },
    "SleepEff": {
      "mean": 0.933817236209041,
      "sd_within": 0.05
    }
  },
  "4": {
    "HRV": {
      "mean": 73.1256602969341,
      "sd_within": 15.0
    },
    "RHR": {
      "mean": 49.475003136329995,
      "sd_within": 5.0
    },
    "SleepDur": {
      "mean": 7.616446959668401,
      "sd_within": 0.8
    },
    "SleepEff": {
      "mean": 0.9263535090392182,
      "sd_within": 0.05
    }
  },
  "5": {
    "HRV": {
      "mean": 78.52110109163792,
      "sd_within": 15.0
    },
    "RHR": {
      "mean": 45.276281822384234,
      "sd_within": 5.0
    },
    "SleepDur": {
      "mean": 8.489016535469613,
      "sd_within": 0.8
    },
    "SleepEff": {
      "mean": 0.8953641155379359,
      "sd_within": 0.05
    }
  },
  "6": {
    "HRV": {
      "mean": 77.18293159609416,
      "sd_within": 15.0
    },
    "RHR": {
      "mean": 50.12923674221339,
      "sd_within": 5.0
    },
    "SleepDur": {
      "mean": 8.146177625745631,
      "sd_within": 0.8
    },
    "SleepEff": {
      "mean": 0.9123819783478797,
      "sd_within": 0.05
    }
  },
  "7": {
    "HRV": {
      "mean": 97.1331808069637,
      "sd_within": 15.0
    },
    "RHR": {
      "mean": 46.37433993446154,
      "sd_within": 5.0
    },
    "SleepDur": {
      "mean": 7.795102908371385,
      "sd_within": 0.8
    },
    "SleepEff": {
      "mean": 0.8755868181525637,
      "sd_within": 0.05
    }
  },
  "8": {
    "HRV": {
      "mean": 89.03177834176714,
      "sd_within": 15.0
    },
    "RHR": {
      "mean": 47.5442101693805,
      "sd_within": 5.0
    },
    "SleepDur": {
      "mean": 7.663937409214989,
      "sd_within": 0.8
    },
    "SleepEff": {
      "mean": 0.8752655635292629,
      "sd_within": 0.05
    }
  },
  "9": {
    "HRV": {
      "mean": 85.94603336962754,
      "sd_within": 15.0
    },
    "RHR": {
      "mean": 50.17261707322078,
      "sd_within": 5.0
    },
    "SleepDur": {
      "mean": 7.733796117084522,
      "sd_within": 0.8
    },
    "SleepEff": {
      "mean": 0.9069648396920016,
      "sd_within": 0.05
    }
  },
  "10": {
    "HRV": {
      "mean": 81.7495087738321,
      "sd_within": 15.0
    },
    "RHR": {
      "mean": 51.48571511179276,
      "sd_within": 5.0
    },
    "SleepDur": {
      "mean": 8.089438219509873,
      "sd_within": 0.8
    },
    "SleepEff": {
      "mean": 0.9203674068921569,
      "sd_within": 0.05
    }
  },
  "11": {
    "HRV": {
      "mean": 82.31295518951987,
      "sd_within": 15.0
    },
    "RHR": {
      "mean": 50.52515290335416,
      "sd_within": 5.0
    },
    "SleepDur": {
      "mean": 7.417137672057733,
      "sd_within": 0.8
    },
    "SleepEff": {
      "mean": 0.890409863509281,
      "sd_within": 0.05
    }
  },
  "12": {
    "HRV": {
      "mean": 74.88897721405327,
      "sd_within": 15.0
    },
    "RHR": {
      "mean": 46.89943099509326,
      "sd_within": 5.0
    },
    "SleepDur": {
      "mean": 8.597976524493758,
      "sd_within": 0.8
    },
    "SleepEff": {
      "mean": 0.8740250665292028,
      "sd_within": 0.05
    }
  },
  "13": {
    "HRV": {
      "mean": 66.53704182707357,
      "sd_within": 15.0
    },
    "RHR": {
      "mean": 46.6604598800569,
      "sd_within": 5.0
    },
    "SleepDur": {
      "mean": 8.065101226042001,
      "sd_within": 0.8
    },
    "SleepEff": {
      "mean": 0.9175866699407784,
      "sd_within": 0.05
    }
  },
  "14": {
    "HRV": {
      "mean": 86.34677788159941,
      "sd_within": 15.0
    },
    "RHR": {
      "mean": 46.60509971100625,
      "sd_within": 5.0
    },
    "SleepDur": {
      "mean": 7.815059282934173,
      "sd_within": 0.8
    },
    "SleepEff": {
      "mean": 0.9257392764377146,
      "sd_within": 0.05
    }
  },
  "15": {
    "HRV": {
      "mean": 69.79450941329662,
      "sd_within": 15.0
    },
    "RHR": {
      "mean": 43.46685114398608,
      "sd_within": 5.0
    },
    "SleepDur": {
      "mean": 7.632219085599355,
      "sd_within": 0.8
    },
    "SleepEff": {
      "mean": 0.9149148223216129,
      "sd_within": 0.05
    }
  },
  "16": {
    "HRV": {
      "mean": 85.52388283254214,
      "sd_within": 15.0
    },
    "RHR": {
      "mean": 46.290989414653865,
      "sd_within": 5.0
    },
    "SleepDur": {
      "mean": 8.063415876430685,
      "sd_within": 0.8
    },
    "SleepEff": {
      "mean": 0.9187677118190202,
      "sd_within": 0.05
    }
  },
  "17": {
    "HRV": {
      "mean": 83.6542019004593,
      "sd_within": 15.0
    },
    "RHR": {
      "mean": 45.3522962357334,
      "sd_within": 5.0
    },
    "SleepDur": {
      "mean": 7.8547784613739715,
      "sd_within": 0.8
    },
    "SleepEff": {
      "mean": 0.8885478631800502,
      "sd_within": 0.05
    }
  },
  "18": {
    "HRV": {
      "mean": 83.89577984628465,
      "sd_within": 15.0
    },
    "RHR": {
      "mean": 46.122390639189106,
      "sd_within": 5.0
    },
    "SleepDur": {
      "mean": 8.004997647491075,
      "sd_within": 0.8
    },
    "SleepEff": {
      "mean": 0.9144223997671773,
      "sd_within": 0.05
    }
  },
  "19": {
    "HRV": {
      "mean": 85.3230808717823,
      "sd_within": 15.0
    },
    "RHR": {
      "mean": 47.60605806196231,
      "sd_within": 5.0
    },
    "SleepDur": {
      "mean": 7.830680675182339,
      "sd_within": 0.8
    },
    "SleepEff": {
      "mean": 0.8976084536728081,
      "sd_within": 0.05
    }
  },
  "20": {
    "HRV": {
      "mean": 68.4231002206153,
      "sd_within": 15.0
    },
    "RHR": {
      "mean": 42.70920155058239,
      "sd_within": 5.0
    },
    "SleepDur": {
      "mean": 7.6011012689594075,
      "sd_within": 0.8
    },
    "SleepEff": {
      "mean": 0.9119932268017031,
      "sd_within": 0.05
    }
  },
  "21": {
    "HRV": {
      "mean": 76.97469956768488,
      "sd_within": 15.0
    },
    "RHR": {
      "mean": 53.19691319114426,
      "sd_within": 5.0
    },
    "SleepDur": {
      "mean": 7.85749441157543,
      "sd_within": 0.8
    },
    "SleepEff": {
      "mean": 0.9221254670540127,
      "sd_within": 0.05
    }
  },
  "22": {
    "HRV": {
      "mean": 78.35649953705897,
      "sd_within": 15.0
    },
    "RHR": {
      "mean": 44.199911780357674,
      "sd_within": 5.0
    },
    "SleepDur": {
      "mean": 7.864386769639775,
      "sd_within": 0.8
    },
    "SleepEff": {
      "mean": 0.9252092441237219,
      "sd_within": 0.05
    }
  },
  "23": {
    "HRV": {
      "mean": 83.47538914836686,
      "sd_within": 15.0
    },
    "RHR": {
      "mean": 48.95094240932911,
      "sd_within": 5.0
    },
    "SleepDur": {
      "mean": 7.762340017721282,
      "sd_within": 0.8
    },
    "SleepEff": {
      "mean": 0.8566182643683464,
      "sd_within": 0.05
    }
  },
  "24": {
    "HRV": {
      "mean": 75.76405832748958,
      "sd_within": 15.0
    },
    "RHR": {
      "mean": 48.930704845418816,
      "sd_within": 5.0
    },
    "SleepDur": {
      "mean": 8.008740858209377,
      "sd_within": 0.8
    },
    "SleepEff": {
      "mean": 0.9480533667396275,
      "sd_within": 0.05
    }
  },
  "25": {
    "HRV": {
      "mean": 71.81202005902509,
      "sd_within": 15.0
    },
    "RHR": {
      "mean": 48.71710253982526,
      "sd_within": 5.0
    },
    "SleepDur": {
      "mean": 8.087998673588706,
      "sd_within": 0.8
    },
    "SleepEff": {
      "mean": 0.9407756272572131,
      "sd_within": 0.05
    }
  },
  "26": {
    "HRV": {
      "mean": 82.85496847319608,
      "sd_within": 15.0
    },
    "RHR": {
      "mean": 53.85321156487825,
      "sd_within": 5.0
    },
    "SleepDur": {
      "mean": 7.52449477827086,
      "sd_within": 0.8
    },
    "SleepEff": {
      "mean": 0.8808074540175076,
      "sd_within": 0.05
    }
  },
  "27": {
    "HRV": {
      "mean": 76.88152157475386,
      "sd_within": 15.0
    },
    "RHR": {
      "mean": 42.49325540977476,
      "sd_within": 5.0
    },
    "SleepDur": {
      "mean": 8.254060378725761,
      "sd_within": 0.8
    },
    "SleepEff": {
      "mean": 0.8933333190870368,
      "sd_within": 0.05
    }
  },
  "28": {
    "HRV": {
      "mean": 71.87536735033967,
      "sd_within": 15.0
    },
    "RHR": {
      "mean": 49.25405538980078,
      "sd_within": 5.0
    },
    "SleepDur": {
      "mean": 8.335250627157752,
      "sd_within": 0.8
    },
    "SleepEff": {
      "mean": 0.9599019267507536,
      "sd_within": 0.05
    }
  },
  "29": {
    "HRV": {
      "mean": 83.31527546620796,
      "sd_within": 15.0
    },
    "RHR": {
      "mean": 44.04184751987254,
      "sd_within": 5.0
    },
    "SleepDur": {
      "mean": 7.147181487707476,
      "sd_within": 0.8
    },
    "SleepEff": {
      "mean": 0.9080313438703151,
      "sd_within": 0.05
    }
  },
  "30": {
    "HRV": {
      "mean": 76.67714191856251,
      "sd_within": 15.0
    },
    "RHR": {
      "mean": 45.55161280376077,
      "sd_within": 5.0
    },
    "SleepDur": {
      "mean": 7.943683645433446,
      "sd_within": 0.8
    },
    "SleepEff": {
      "mean": 0.9319794069236293,
      "sd_within": 0.05
    }
  },
  "31": {
    "HRV": {
      "mean": 78.7309213036905,
      "sd_within": 15.0
    },
    "RHR": {
      "mean": 43.85738498869675,
      "sd_within": 5.0
    },
    "SleepDur": {
      "mean": 7.330126822118257,
      "sd_within": 0.8
    },
    "SleepEff": {
      "mean": 0.8854107627278001,
      "sd_within": 0.05
    }
  },
  "32": {
    "HRV": {
      "mean": 94.14343930863906,
      "sd_within": 15.0
    },
    "RHR": {
      "mean": 48.521098085891545,
      "sd_within": 5.0
    },
    "SleepDur": {
      "mean": 8.393095804409223,
      "sd_within": 0.8
    },
    "SleepEff": {
      "mean": 0.8850211320438255,
      "sd_within": 0.05
    }
  },
  "33": {
    "HRV": {
      "mean": 72.27906590214103,
      "sd_within": 15.0
    },
    "RHR": {
      "mean": 45.099095741856985,
      "sd_within": 5.0
    },
    "SleepDur": {
      "mean": 8.851387892974065,
      "sd_within": 0.8
    },
    "SleepEff": {
      "mean": 0.8753583996232684,
      "sd_within": 0.05
    }
  },
  "34": {
    "HRV": {
      "mean": 72.77658257530379,
      "sd_within": 15.0
    },
    "RHR": {
      "mean": 51.726292051496976,
      "sd_within": 5.0
    },
    "SleepDur": {
      "mean": 8.153980386442345,
      "sd_within": 0.8
    },
    "SleepEff": {
      "mean": 0.8953008630702574,
      "sd_within": 0.05
    }
  },
  "35": {
    "HRV": {
      "mean": 74.76169843656487,
      "sd_within": 15.0
    },
    "RHR": {
      "mean": 49.78428880592832,
      "sd_within": 5.0
    },
    "SleepDur": {
      "mean": 7.818006607863688,
      "sd_within": 0.8
    },
    "SleepEff": {
      "mean": 0.8632318270869825,
      "sd_within": 0.05
    }
  },
  "36": {
    "HRV": {
      "mean": 81.38070334177695,
      "sd_within": 15.0
    },
    "RHR": {
      "mean": 54.31636502564174,
      "sd_within": 5.0
    },
    "SleepDur": {
      "mean": 8.063996645429375,
      "sd_within": 0.8
    },
    "SleepEff": {
      "mean": 0.8964408502167035,
      "sd_within": 0.05
    }
  },
  "37": {
    "HRV": {
      "mean": 90.4480139336546,
      "sd_within": 15.0
    },
    "RHR": {
      "mean": 48.87753000545543,
      "sd_within": 5.0
    },
    "SleepDur": {
      "mean": 7.835629107666505,
      "sd_within": 0.8
    },
    "SleepEff": {
      "mean": 0.9331886613017967,
      "sd_within": 0.05
    }
  },
  "38": {
    "HRV": {
      "mean": 92.28604793596793,
      "sd_within": 15.0
    },
    "RHR": {
      "mean": 48.73293774888762,
      "sd_within": 5.0
    },
    "SleepDur": {
      "mean": 7.5102123873118,
      "sd_within": 0.8
    },
    "SleepEff": {
      "mean": 0.85895522402263,
      "sd_within": 0.05
    }
  },
  "39": {
    "HRV": {
      "mean": 93.78932576626637,
      "sd_within": 15.0
    },
    "RHR": {
      "mean": 47.281923146869595,
      "sd_within": 5.0
    },
    "SleepDur": {
      "mean": 7.846725071545605,
      "sd_within": 0.8
    },
    "SleepEff": {
      "mean": 0.9438433287672661,
      "sd_within": 0.05
    }
  },
  "40": {
    "HRV": {
      "mean": 72.84218384835339,
      "sd_within": 15.0
    },
    "RHR": {
      "mean": 50.57330717875618,
      "sd_within": 5.0
    },
    "SleepDur": {
      "mean": 7.842157950856164,
      "sd_within": 0.8
    },
    "SleepEff": {
      "mean": 0.8998463439983979,
      "sd_within": 0.05
    }
  },
  "41": {
    "HRV": {
      "mean": 82.70059639039147,
      "sd_within": 15.0
    },
    "RHR": {
      "mean": 53.629927445254864,
      "sd_within": 5.0
    },
    "SleepDur": {
      "mean": 8.036233962760699,
      "sd_within": 0.8
    },
    "SleepEff": {
      "mean": 0.9193181637983058,
      "sd_within": 0.05
    }
  },
  "42": {
    "HRV": {
      "mean": 79.61025278455905,
      "sd_within": 15.0
    },
    "RHR": {
      "mean": 44.627078918828516,
      "sd_within": 5.0
    },
    "SleepDur": {
      "mean": 7.512474775830549,
      "sd_within": 0.8
    },
    "SleepEff": {
      "mean": 0.8736554289921376,
      "sd_within": 0.05
    }
  },
  "43": {
    "HRV": {
      "mean": 87.32722033884811,
      "sd_within": 15.0
    },
    "RHR": {
      "mean": 42.694429129041744,
      "sd_within": 5.0
    },
    "SleepDur": {
      "mean": 8.012252597037767,
      "sd_within": 0.8
    },
    "SleepEff": {
      "mean": 0.8854749169999927,
      "sd_within": 0.05
    }
  },
  "44": {
    "HRV": {
      "mean": 88.02206260243683,
      "sd_within": 15.0
    },
    "RHR": {
      "mean": 50.1524617480157,
      "sd_within": 5.0
    },
    "SleepDur": {
      "mean": 8.534959242977097,
      "sd_within": 0.8
    },
    "SleepEff": {
      "mean": 0.895364829622503,
      "sd_within": 0.05
    }
  },
  "45": {
    "HRV": {
      "mean": 78.209129464956,
      "sd_within": 15.0
    },
    "RHR": {
      "mean": 48.96998716508489,
      "sd_within": 5.0
    },
    "SleepDur": {
      "mean": 8.070629343381484,
      "sd_within": 0.8
    },
    "SleepEff": {
      "mean": 0.867468357832999,
      "sd_within": 0.05
    }
  },
  "46": {
    "HRV": {
      "mean": 81.82582664111123,
      "sd_within": 15.0
    },
    "RHR": {
      "mean": 58.06989615013568,
      "sd_within": 5.0
    },
    "SleepDur": {
      "mean": 8.750737844512669,
      "sd_within": 0.8
    },
    "SleepEff": {
      "mean": 0.8744026994832355,
      "sd_within": 0.05
    }
  },
  "47": {
    "HRV": {
      "mean": 68.29246398530398,
      "sd_within": 15.0
    },
    "RHR": {
      "mean": 45.637171944146054,
      "sd_within": 5.0
    },
    "SleepDur": {
      "mean": 8.126242001436136,
      "sd_within": 0.8
    },
    "SleepEff": {
      "mean": 0.9361756086266471,
      "sd_within": 0.05
    }
  },
  "48": {
    "HRV": {
      "mean": 74.76682847945763,
      "sd_within": 15.0
    },
    "RHR": {
      "mean": 39.41084388104538,
      "sd_within": 5.0
    },
    "SleepDur": {
      "mean": 7.934933631782037,
      "sd_within": 0.8
    },
    "SleepEff": {
      "mean": 0.8681275676442132,
      "sd_within": 0.05
    }
  },
  "49": {
    "HRV": {
      "mean": 72.9851137746593,
      "sd_within": 15.0
    },
    "RHR": {
      "mean": 47.62294978298977,
      "sd_within": 5.0
    },
    "SleepDur": {
      "mean": 7.296908643457347,
      "sd_within": 0.8
    },
    "SleepEff": {
      "mean": 0.8559886426382703,
      "sd_within": 0.05
    }
  },
  "50": {
    "HRV": {
      "mean": 69.70061934980775,
      "sd_within": 15.0
    },
    "RHR": {
      "mean": 43.61285768618144,
      "sd_within": 5.0
    },
    "SleepDur": {
      "mean": 8.734765411328526,
      "sd_within": 0.8
    },
    "SleepEff": {
      "mean": 0.9871520150772122,
      "sd_within": 0.05
    }
  },
  "51": {
    "HRV": {
      "mean": 77.05400834569575,
      "sd_within": 15.0
    },
    "RHR": {
      "mean": 49.366222203762035,
      "sd_within": 5.0
    },
    "SleepDur": {
      "mean": 8.691479057762237,
      "sd_within": 0.8
    },
    "SleepEff": {
      "mean": 0.8703942876471529,
      "sd_within": 0.05
    }
  },
  "52": {
    "HRV": {
      "mean": 86.21870060849395,
      "sd_within": 15.0
    },
    "RHR": {
      "mean": 49.73906429786648,
      "sd_within": 5.0
    },
    "SleepDur": {
      "mean": 7.849537571507961,
      "sd_within": 0.8
    },
    "SleepEff": {
      "mean": 0.8959853110645188,
      "sd_within": 0.05
    }
  },
  "53": {
    "HRV": {
      "mean": 78.09461004820268,
      "sd_within": 15.0
    },
    "RHR": {
      "mean": 46.934450039964176,
      "sd_within": 5.0
    },
    "SleepDur": {
      "mean": 8.092867955850503,
      "sd_within": 0.8
    },
    "SleepEff": {
      "mean": 0.8833401834354295,
      "sd_within": 0.05
    }
  },
  "54": {
    "HRV": {
      "mean": 88.10172654255862,
      "sd_within": 15.0
    },
    "RHR": {
      "mean": 48.621717310673866,
      "sd_within": 5.0
    },
    "SleepDur": {
      "mean": 8.140702563359682,
      "sd_within": 0.8
    },
    "SleepEff": {
      "mean": 0.901594660427336,
      "sd_within": 0.05
    }
  },
  "55": {
    "HRV": {
      "mean": 74.22753573165723,
      "sd_within": 15.0
    },
    "RHR": {
      "mean": 49.26597704669323,
      "sd_within": 5.0
    },
    "SleepDur": {
      "mean": 7.961085360634605,
      "sd_within": 0.8
    },
    "SleepEff": {
      "mean": 0.9627950492679178,
      "sd_within": 0.05
    }
  },
  "56": {
    "HRV": {
      "mean": 83.08677242045201,
      "sd_within": 15.0
    },
    "RHR": {
      "mean": 44.94777116122093,
      "sd_within": 5.0
    },
    "SleepDur": {
      "mean": 7.5550354112066325,
      "sd_within": 0.8
    },
    "SleepEff": {
      "mean": 0.9357342885926659,
      "sd_within": 0.05
    }
  },
  "57": {
    "HRV": {
      "mean": 83.8411472271329,
      "sd_within": 15.0
    },
    "RHR": {
      "mean": 41.02165605210323,
      "sd_within": 5.0
    },
    "SleepDur": {
      "mean": 8.370975392623272,
      "sd_within": 0.8
    },
    "SleepEff": {
      "mean": 0.9136326101464309,
      "sd_within": 0.05
    }
  },
  "58": {
    "HRV": {
      "mean": 76.2278015404004,
      "sd_within": 15.0
    },
    "RHR": {
      "mean": 49.054868817426076,
      "sd_within": 5.0
    },
    "SleepDur": {
      "mean": 8.020986719342497,
      "sd_within": 0.8
    },
    "SleepEff": {
      "mean": 0.8912348644258934,
      "sd_within": 0.05
    }
  },
  "59": {
    "HRV": {
      "mean": 77.98418097434492,
      "sd_within": 15.0
    },
    "RHR": {
      "mean": 48.610250048409874,
      "sd_within": 5.0
    },
    "SleepDur": {
      "mean": 8.588596789197263,
      "sd_within": 0.8
    },
    "SleepEff": {
      "mean": 0.8230002467720611,
      "sd_within": 0.05
    }
  },
  "60": {
    "HRV": {
      "mean": 81.41209937097958,
      "sd_within": 15.0
    },
    "RHR": {
      "mean": 49.1839759587484,
      "sd_within": 5.0
    },
    "SleepDur": {
      "mean": 7.851234167471484,
      "sd_within": 0.8
    },
    "SleepEff": {
      "mean": 0.8472983465256425,
      "sd_within": 0.05
    }
  },
  "61": {
    "HRV": {
      "mean": 93.81880171331348,
      "sd_within": 15.0
    },
    "RHR": {
      "mean": 41.86455438033545,
      "sd_within": 5.0
    },
    "SleepDur": {
      "mean": 8.345531205479276,
      "sd_within": 0.8
    },
    "SleepEff": {
      "mean": 0.8901442433063133,
      "sd_within": 0.05
    }
  },
  "62": {
    "HRV": {
      "mean": 71.5768119143684,
      "sd_within": 15.0
    },
    "RHR": {
      "mean": 46.662175310576494,
      "sd_within": 5.0
    },
    "SleepDur": {
      "mean": 8.520017837879584,
      "sd_within": 0.8
    },
    "SleepEff": {
      "mean": 0.9174796572596312,
      "sd_within": 0.05
    }
  },
  "63": {
    "HRV": {
      "mean": 89.41929511182155,
      "sd_within": 15.0
    },
    "RHR": {
      "mean": 49.75634671571831,
      "sd_within": 5.0
    },
    "SleepDur": {
      "mean": 8.697573810467118,
      "sd_within": 0.8
    },
    "SleepEff": {
      "mean": 0.913169794762149,
      "sd_within": 0.05
    }
  },
  "64": {
    "HRV": {
      "mean": 77.62743237172234,
      "sd_within": 15.0
    },
    "RHR": {
      "mean": 48.26618326343682,
      "sd_within": 5.0
    },
    "SleepDur": {
      "mean": 7.72103047067989,
      "sd_within": 0.8
    },
    "SleepEff": {
      "mean": 0.9296875180378457,
      "sd_within": 0.05
    }
  },
  "65": {
    "HRV": {
      "mean": 86.25880273934129,
      "sd_within": 15.0
    },
    "RHR": {
      "mean": 47.237395769979365,
      "sd_within": 5.0
    },
    "SleepDur": {
      "mean": 8.468498837386928,
      "sd_within": 0.8
    },
    "SleepEff": {
      "mean": 0.9225260696619378,
      "sd_within": 0.05
    }
  },
  "66": {
    "HRV": {
      "mean": 85.84619752910916,
      "sd_within": 15.0
    },
    "RHR": {
      "mean": 41.71183897738704,
      "sd_within": 5.0
    },
    "SleepDur": {
      "mean": 7.97321873084072,
      "sd_within": 0.8
    },
    "SleepEff": {
      "mean": 0.8648397842221556,
      "sd_within": 0.05
    }
  },
  "67": {
    "HRV": {
      "mean": 92.08982746621378,
      "sd_within": 15.0
    },
    "RHR": {
      "mean": 50.55013524359079,
      "sd_within": 5.0
    },
    "SleepDur": {
      "mean": 7.720427828568502,
      "sd_within": 0.8
    },
    "SleepEff": {
      "mean": 0.869588479006788,
      "sd_within": 0.05
    }
  },
  "68": {
    "HRV": {
      "mean": 70.26751880495098,
      "sd_within": 15.0
    },
    "RHR": {
      "mean": 45.315438890413674,
      "sd_within": 5.0
    },
    "SleepDur": {
      "mean": 8.124803788620497,
      "sd_within": 0.8
    },
    "SleepEff": {
      "mean": 0.9346593610832009,
      "sd_within": 0.05
    }
  },
  "69": {
    "HRV": {
      "mean": 61.669683931215204,
      "sd_within": 15.0
    },
    "RHR": {
      "mean": 49.21746691612104,
      "sd_within": 5.0
    },
    "SleepDur": {
      "mean": 8.02881342929303,
      "sd_within": 0.8
    },
    "SleepEff": {
      "mean": 0.9124167085611808,
      "sd_within": 0.05
    }
  },
  "70": {
    "HRV": {
      "mean": 63.49409378556206,
      "sd_within": 15.0
    },
    "RHR": {
      "mean": 45.63558629923558,
      "sd_within": 5.0
    },
    "SleepDur": {
      "mean": 8.236362529117342,
      "sd_within": 0.8
    },
    "SleepEff": {
      "mean": 0.8525521680163818,
      "sd_within": 0.05
    }
  },
  "71": {
    "HRV": {
      "mean": 82.94685290160527,
      "sd_within": 15.0
    },
    "RHR": {
      "mean": 51.386335943373616,
      "sd_within": 5.0
    },
    "SleepDur": {
      "mean": 7.771622535391282,
      "sd_within": 0.8
    },
    "SleepEff": {
      "mean": 0.9244129106989863,
      "sd_within": 0.05
    }
  },
  "72": {
    "HRV": {
      "mean": 81.86302416109734,
      "sd_within": 15.0
    },
    "RHR": {
      "mean": 48.937603570794785,
      "sd_within": 5.0
    },
    "SleepDur": {
      "mean": 8.108137295712691,
      "sd_within": 0.8
    },
    "SleepEff": {
      "mean": 0.8740996420578185,
      "sd_within": 0.05
    }
  },
  "73": {
    "HRV": {
      "mean": 78.77981974038113,
      "sd_within": 15.0
    },
    "RHR": {
      "mean": 49.53357545741398,
      "sd_within": 5.0
    },
    "SleepDur": {
      "mean": 8.399929698764119,
      "sd_within": 0.8
    },
    "SleepEff": {
      "mean": 0.8682439175406478,
      "sd_within": 0.05
    }
  },
  "74": {
    "HRV": {
      "mean": 91.85164438127178,
      "sd_within": 15.0
    },
    "RHR": {
      "mean": 45.02564708474974,
      "sd_within": 5.0
    },
    "SleepDur": {
      "mean": 7.671099993083872,
      "sd_within": 0.8
    },
    "SleepEff": {
      "mean": 0.9060691857549358,
      "sd_within": 0.05
    }
  },
  "75": {
    "HRV": {
      "mean": 80.09140844448527,
      "sd_within": 15.0
    },
    "RHR": {
      "mean": 53.315842361747954,
      "sd_within": 5.0
    },
    "SleepDur": {
      "mean": 8.342717593026611,
      "sd_within": 0.8
    },
    "SleepEff": {
      "mean": 0.9252546020067018,
      "sd_within": 0.05
    }
  },
  "76": {
    "HRV": {
      "mean": 98.62122480276868,
      "sd_within": 15.0
    },
    "RHR": {
      "mean": 47.179353244535825,
      "sd_within": 5.0
    },
    "SleepDur": {
      "mean": 7.198591083173394,
      "sd_within": 0.8
    },
    "SleepEff": {
      "mean": 0.9481276308455142,
      "sd_within": 0.05
    }
  },
  "77": {
    "HRV": {
      "mean": 80.86304355474427,
      "sd_within": 15.0
    },
    "RHR": {
      "mean": 53.23820273944211,
      "sd_within": 5.0
    },
    "SleepDur": {
      "mean": 7.35909618357643,
      "sd_within": 0.8
    },
    "SleepEff": {
      "mean": 0.8624505835768158,
      "sd_within": 0.05
    }
  },
  "78": {
    "HRV": {
      "mean": 73.64690967979661,
      "sd_within": 15.0
    },
    "RHR": {
      "mean": 49.75854642406797,
      "sd_within": 5.0
    },
    "SleepDur": {
      "mean": 8.209675137125108,
      "sd_within": 0.8
    },
    "SleepEff": {
      "mean": 0.9082882253798567,
      "sd_within": 0.05
    }
  },
  "79": {
    "HRV": {
      "mean": 61.519172506938844,
      "sd_within": 15.0
    },
    "RHR": {
      "mean": 48.21741434156153,
      "sd_within": 5.0
    },
    "SleepDur": {
      "mean": 7.811289586544666,
      "sd_within": 0.8
    },
    "SleepEff": {
      "mean": 0.9137815731514983,
      "sd_within": 0.05
    }
  },
  "80": {
    "HRV": {
      "mean": 81.10593145646945,
      "sd_within": 15.0
    },
    "RHR": {
      "mean": 51.040532341503415,
      "sd_within": 5.0
    },
    "SleepDur": {
      "mean": 8.091684549646027,
      "sd_within": 0.8
    },
    "SleepEff": {
      "mean": 0.915901941168044,
      "sd_within": 0.05
    }
  },
  "81": {
    "HRV": {
      "mean": 78.56310868934833,
      "sd_within": 15.0
    },
    "RHR": {
      "mean": 48.78710438662783,
      "sd_within": 5.0
    },
    "SleepDur": {
      "mean": 8.328211390166967,
      "sd_within": 0.8
    },
    "SleepEff": {
      "mean": 0.8881877648332629,
      "sd_within": 0.05
    }
  },
  "82": {
    "HRV": {
      "mean": 77.87328966467697,
      "sd_within": 15.0
    },
    "RHR": {
      "mean": 47.52983133068748,
      "sd_within": 5.0
    },
    "SleepDur": {
      "mean": 8.331807616809629,
      "sd_within": 0.8
    },
    "SleepEff": {
      "mean": 0.8402081888683753,
      "sd_within": 0.05
    }
  },
  "83": {
    "HRV": {
      "mean": 68.14251682045743,
      "sd_within": 15.0
    },
    "RHR": {
      "mean": 38.66553552060678,
      "sd_within": 5.0
    },
    "SleepDur": {
      "mean": 7.7286942239379295,
      "sd_within": 0.8
    },
    "SleepEff": {
      "mean": 0.9224830169918322,
      "sd_within": 0.05
    }
  },
  "84": {
    "HRV": {
      "mean": 81.58232065553482,
      "sd_within": 15.0
    },
    "RHR": {
      "mean": 52.35686998684317,
      "sd_within": 5.0
    },
    "SleepDur": {
      "mean": 8.531074452907077,
      "sd_within": 0.8
    },
    "SleepEff": {
      "mean": 0.8979258619582159,
      "sd_within": 0.05
    }
  },
  "85": {
    "HRV": {
      "mean": 80.73701326747288,
      "sd_within": 15.0
    },
    "RHR": {
      "mean": 44.65040710469015,
      "sd_within": 5.0
    },
    "SleepDur": {
      "mean": 7.7622398591205055,
      "sd_within": 0.8
    },
    "SleepEff": {
      "mean": 0.8555839046230496,
      "sd_within": 0.05
    }
  },
  "86": {
    "HRV": {
      "mean": 77.13586649540457,
      "sd_within": 15.0
    },
    "RHR": {
      "mean": 51.21434007751441,
      "sd_within": 5.0
    },
    "SleepDur": {
      "mean": 8.688307932466394,
      "sd_within": 0.8
    },
    "SleepEff": {
      "mean": 0.8585345545386889,
      "sd_within": 0.05
    }
  },
  "87": {
    "HRV": {
      "mean": 71.67564848673973,
      "sd_within": 15.0
    },
    "RHR": {
      "mean": 49.89878835385281,
      "sd_within": 5.0
    },
    "SleepDur": {
      "mean": 7.9475653397249095,
      "sd_within": 0.8
    },
    "SleepEff": {
      "mean": 0.8450728252245742,
      "sd_within": 0.05
    }
  },
  "88": {
    "HRV": {
      "mean": 75.15999429753015,
      "sd_within": 15.0
    },
    "RHR": {
      "mean": 45.86439904650578,
      "sd_within": 5.0
    },
    "SleepDur": {
      "mean": 7.572099035484124,
      "sd_within": 0.8
    },
    "SleepEff": {
      "mean": 0.8803715016993734,
      "sd_within": 0.05
    }
  },
  "89": {
    "HRV": {
      "mean": 78.48604527250876,
      "sd_within": 15.0
    },
    "RHR": {
      "mean": 49.314648009129925,
      "sd_within": 5.0
    },
    "SleepDur": {
      "mean": 8.144768741571538,
      "sd_within": 0.8
    },
    "SleepEff": {
      "mean": 0.939619849665845,
      "sd_within": 0.05
    }
  },
  "90": {
    "HRV": {
      "mean": 68.18513746523415,
      "sd_within": 15.0
    },
    "RHR": {
      "mean": 52.26888966628793,
      "sd_within": 5.0
    },
    "SleepDur": {
      "mean": 7.867404731161098,
      "sd_within": 0.8
    },
    "SleepEff": {
      "mean": 0.9334377733373214,
      "sd_within": 0.05
    }
  },
  "91": {
    "HRV": {
      "mean": 78.95089975837324,
      "sd_within": 15.0
    },
    "RHR": {
      "mean": 49.39510357618518,
      "sd_within": 5.0
    },
    "SleepDur": {
      "mean": 8.78040502405052,
      "sd_within": 0.8
    },
    "SleepEff": {
      "mean": 0.9623094158716126,
      "sd_within": 0.05
    }
  },
  "92": {
    "HRV": {
      "mean": 81.2815247465366,
      "sd_within": 15.0
    },
    "RHR": {
      "mean": 52.30496062986554,
      "sd_within": 5.0
    },
    "SleepDur": {
      "mean": 7.6617355868930614,
      "sd_within": 0.8
    },
    "SleepEff": {
      "mean": 0.9099921111785477,
      "sd_within": 0.05
    }
  },
  "93": {
    "HRV": {
      "mean": 82.51126569166043,
      "sd_within": 15.0
    },
    "RHR": {
      "mean": 44.66652477620238,
      "sd_within": 5.0
    },
    "SleepDur": {
      "mean": 7.364173002676412,
      "sd_within": 0.8
    },
    "SleepEff": {
      "mean": 0.8378104969202613,
      "sd_within": 0.05
    }
  },
  "94": {
    "HRV": {
      "mean": 76.33059772048533,
      "sd_within": 15.0
    },
    "RHR": {
      "mean": 46.82723365340495,
      "sd_within": 5.0
    },
    "SleepDur": {
      "mean": 8.774892464971806,
      "sd_within": 0.8
    },
    "SleepEff": {
      "mean": 0.933179801097219,
      "sd_within": 0.05
    }
  },
  "95": {
    "HRV": {
      "mean": 82.78166761960766,
      "sd_within": 15.0
    },
    "RHR": {
      "mean": 46.3716870545987,
      "sd_within": 5.0
    },
    "SleepDur": {
      "mean": 7.886254464783962,
      "sd_within": 0.8
    },
    "SleepEff": {
      "mean": 0.9055597694824615,
      "sd_within": 0.05
    }
  },
  "96": {
    "HRV": {
      "mean": 77.28593212892788,
      "sd_within": 15.0
    },
    "RHR": {
      "mean": 52.25540613093743,
      "sd_within": 5.0
    },
    "SleepDur": {
      "mean": 7.543224709543038,
      "sd_within": 0.8
    },
    "SleepEff": {
      "mean": 0.900190171870868,
      "sd_within": 0.05
    }
  },
  "97": {
    "HRV": {
      "mean": 81.7846379410022,
      "sd_within": 15.0
    },
    "RHR": {
      "mean": 53.732858026424694,
      "sd_within": 5.0
    },
    "SleepDur": {
      "mean": 8.036608071269283,
      "sd_within": 0.8
    },
    "SleepEff": {
      "mean": 0.9174233128598939,
      "sd_within": 0.05
    }
  },
  "98": {
    "HRV": {
      "mean": 78.63673935068637,
      "sd_within": 15.0
    },
    "RHR": {
      "mean": 44.88207041309832,
      "sd_within": 5.0
    },
    "SleepDur": {
      "mean": 8.172120543583022,
      "sd_within": 0.8
    },
    "SleepEff": {
      "mean": 0.8744538843244269,
      "sd_within": 0.05
    }
  },
  "99": {
    "HRV": {
      "mean": 88.68229603556728,
      "sd_within": 15.0
    },
    "RHR": {
      "mean": 49.46612562894892,
      "sd_within": 5.0
    },
    "SleepDur": {
      "mean": 7.885500506577723,
      "sd_within": 0.8
    },
    "SleepEff": {
      "mean": 0.913618967379261,
      "sd_within": 0.05
    }
  },
  "100": {
    "HRV": {
      "mean": 87.48437700372119,
      "sd_within": 15.0
    },
    "RHR": {
      "mean": 40.67437566313951,
      "sd_within": 5.0
    },
    "SleepDur": {
      "mean": 7.865757052752541,
      "sd_within": 0.8
    },
    "SleepEff": {
      "mean": 0.8402756401462801,
      "sd_within": 0.05
    }
  }
}